codebatcher/__init__.py
codebatcher/cbatch.py
codebatcher-0.1.4.dist-info/METADATA
codebatcher-0.1.4.dist-info/WHEEL
codebatcher-0.1.4.dist-info/entry_points.txt
codebatcher-0.1.4.dist-info/RECORD
