Metadata-Version: 2.3
Name: codebatcher
Version: 0.1.4
Summary: Codebase Batcher (cbatch) - CLI tool to output codebase to structured file for AI context.
Author: Zach
Author-email: zh93@nau.edu
Requires-Python: >=3.7
Classifier: Programming Language :: Python :: 3
Classifier: Programming Language :: Python :: 3.7
Classifier: Programming Language :: Python :: 3.8
Classifier: Programming Language :: Python :: 3.9
Classifier: Programming Language :: Python :: 3.10
Classifier: Programming Language :: Python :: 3.11
Classifier: Programming Language :: Python :: 3.12
Classifier: Programming Language :: Python :: 3.13
Requires-Dist: configparser (>=5.3,<6.0)
